digicom
