Metadata-Version: 2.1
Name: digicom
Version: 0.0.2
Summary: UNKNOWN
Home-page: https://github.com/gut-gud-1/
Author: Dane Morgan
Author-email: danemorgan91@gmail.com
License: UNKNOWN
Platform: UNKNOWN
Classifier: Programming Language :: Python :: 3
Classifier: License :: OSI Approved :: MIT License
Classifier: Operating System :: OS Independent
